maplestory_openapi/__init__.py
maplestory_openapi/api/__init__.py
maplestory_openapi/api/utils.py
maplestory_openapi/api/common/__init__.py
maplestory_openapi/api/common/maplestory_api.py
maplestory_openapi/api/common/maplestory_api_error.py
maplestory_openapi/api/common/maplestory_friends_api.py
maplestory_openapi/api/common/enum/__init__.py
maplestory_openapi/api/common/enum/character_image.py
maplestory_openapi/api/common/param/__init__.py
maplestory_openapi/api/common/param/character_image_option.py
maplestory_openapi/api/kms/__init__.py
maplestory_openapi/api/kms/maplestory_api.py
maplestory_openapi/api/kms/maplestory_friends_api.py
maplestory_openapi/api/kms/dto/__init__.py
maplestory_openapi/api/kms/dto/character/__init__.py
maplestory_openapi/api/kms/dto/character/character.py
maplestory_openapi/api/kms/dto/character/character_ability.py
maplestory_openapi/api/kms/dto/character/character_android_equipment.py
maplestory_openapi/api/kms/dto/character/character_basic.py
maplestory_openapi/api/kms/dto/character/character_beauty_equipment.py
maplestory_openapi/api/kms/dto/character/character_cashitem_equipment.py
maplestory_openapi/api/kms/dto/character/character_dojang.py
maplestory_openapi/api/kms/dto/character/character_hexamatrix.py
maplestory_openapi/api/kms/dto/character/character_hexamatrix_stat.py
maplestory_openapi/api/kms/dto/character/character_hyper_stat.py
maplestory_openapi/api/kms/dto/character/character_image.py
maplestory_openapi/api/kms/dto/character/character_item_equipment.py
maplestory_openapi/api/kms/dto/character/character_link_skill.py
maplestory_openapi/api/kms/dto/character/character_other_stat.py
maplestory_openapi/api/kms/dto/character/character_pet_equipment.py
maplestory_openapi/api/kms/dto/character/character_popularity.py
maplestory_openapi/api/kms/dto/character/character_propensity.py
maplestory_openapi/api/kms/dto/character/character_ring_exchange_skill_equipment.py
maplestory_openapi-3.8.1.dist-info/METADATA
maplestory_openapi-3.8.1.dist-info/WHEEL
maplestory_openapi-3.8.1.dist-info/top_level.txt
maplestory_openapi-3.8.1.dist-info/RECORD
