Metadata-Version: 2.4
Name: maplestory_openapi
Version: 3.8.1
Summary: This Python library enables the use of the MapleStory OpenAPI of Nexon.
Home-page: https://github.com/SpiralMoon/maplestory.openapi
Author: so99ynoodles
License: MIT
Requires-Python: >=3.9
Requires-Dist: requests
Requires-Dist: pydantic>=2.5.3
Dynamic: author
Dynamic: description
Dynamic: description-content-type
Dynamic: home-page
Dynamic: license
Dynamic: requires-dist
Dynamic: requires-python
Dynamic: summary
